MANIFEST.in
README.rst
pytest_greendots.py
setup.py
pytest_greendots.egg-info/PKG-INFO
pytest_greendots.egg-info/SOURCES.txt
pytest_greendots.egg-info/dependency_links.txt
pytest_greendots.egg-info/entry_points.txt
pytest_greendots.egg-info/requires.txt
pytest_greendots.egg-info/top_level.txt